{"id": 10400, "name": "Guardian Drake", "qualified_name": "Guardian Drake", "examine": "It's really winging the whole dragon thing, isn't it?", "members": true, "release_date": "2020-07-23", "attributes": ["dragon"], "size": 5, "aggressive": false, "poisonous": false, "immune_poison": true, "immune_venom": false, "max_hit": 0, "attack_types": ["melee", "ranged"], "attack_speed": 0, "wiki_url": "https://oldschool.runescape.wiki/w/Guardian_Drake", "slayer": {"masters": ["konar", "nieve", "duradel"], "level": 84, "xp": 7245.0, "categories": ["drake"]}, "levels": {"combat": 386, "hitpoints": 630, "attack": 270, "strength": 280, "defence": 200, "magic": 300, "ranged": 240}, "bonuses": {"attack": {"melee": 0, "ranged": 40, "magic": 0}, "defence": {"stab": 60, "slash": 100, "crush": 100, "magic": 20, "ranged": 150}, "strength": {"melee": 12, "ranged": 0, "magic": 0}}, "drops": [{"id": 22783, "members": true, "quantity": {"__typename": "ItemDropQuantityScalar", "quantity": 1}, "noted": false, "rarity": 1.0}, {"id": 22960, "members": true, "quantity": {"__typename": "ItemDropQuantityScalar", "quantity": 1}, "noted": false, "rarity": 0.000390625}, {"id": 22957, "members": true, "quantity": {"__typename": "ItemDropQuantityScalar", "quantity": 1}, "noted": false, "rarity": 0.000390625}, {"id": 20849, "members": true, "quantity": {"__typename": "ItemDropQuantityRange", "min": 100, "max": 200}, "noted": false, "rarity": 0.0001}, {"id": 22804, "members": true, "quantity": {"__typename": "ItemDropQuantityRange", "min": 100, "max": 200}, "noted": false, "rarity": 0.0001}, {"id": 1163, "members": true, "quantity": {"__typename": "ItemDropQuantityScalar", "quantity": 1}, "noted": false, "rarity": 0.03529411764705882}, {"id": 2501, "members": true, "quantity": {"__typename": "ItemDropQuantityScalar", "quantity": 1}, "noted": false, "rarity": 0.023529411764705882}, {"id": 2491, "members": true, "quantity": {"__typename": "ItemDropQuantityScalar", "quantity": 1}, "noted": false, "rarity": 0.011764705882352941}, {"id": 1407, "members": true, "quantity": {"__typename": "ItemDropQuantityScalar", "quantity": 1}, "noted": false, "rarity": 0.011764705882352941}, {"id": 1434, "members": true, "quantity": {"__typename": "ItemDropQuantityScalar", "quantity": 1}, "noted": false, "rarity": 0.011764705882352941}, {"id": 554, "members": true, "quantity": {"__typename": "ItemDropQuantityRange", "min": 100, "max": 200}, "noted": false, "rarity": 0.11764705882352941}, {"id": 561, "members": true, "quantity": {"__typename": "ItemDropQuantityRange", "min": 30, "max": 60}, "noted": false, "rarity": 0.11764705882352941}, {"id": 563, "members": true, "quantity": {"__typename": "ItemDropQuantityRange", "min": 25, "max": 50}, "noted": false, "rarity": 0.11764705882352941}, {"id": 560, "members": true, "quantity": {"__typename": "ItemDropQuantityRange", "min": 20, "max": 40}, "noted": false, "rarity": 0.11764705882352941}, {"id": 892, "members": true, "quantity": {"__typename": "ItemDropQuantityRange", "min": 35, "max": 65}, "noted": false, "rarity": 0.11764705882352941}, {"id": 211, "members": true, "quantity": {"__typename": "ItemDropQuantityRange", "min": 1, "max": 3}, "noted": true, "rarity": 0.011025358324145534}, {"id": 213, "members": true, "quantity": {"__typename": "ItemDropQuantityRange", "min": 1, "max": 3}, "noted": true, "rarity": 0.011025358324145534}, {"id": 207, "members": true, "quantity": {"__typename": "ItemDropQuantityRange", "min": 1, "max": 3}, "noted": true, "rarity": 0.008826125330979701}, {"id": 3051, "members": true, "quantity": {"__typename": "ItemDropQuantityRange", "min": 1, "max": 3}, "noted": true, "rarity": 0.008826125330979701}, {"id": 215, "members": true, "quantity": {"__typename": "ItemDropQuantityRange", "min": 1, "max": 3}, "noted": true, "rarity": 0.008826125330979701}, {"id": 217, "members": true, "quantity": {"__typename": "ItemDropQuantityRange", "min": 1, "max": 3}, "noted": true, "rarity": 0.008826125330979701}, {"id": 2485, "members": true, "quantity": {"__typename": "ItemDropQuantityRange", "min": 1, "max": 3}, "noted": true, "rarity": 0.0066181336863004635}, {"id": 219, "members": true, "quantity": {"__typename": "ItemDropQuantityRange", "min": 1, "max": 3}, "noted": true, "rarity": 0.0066181336863004635}, {"id": 617, "members": true, "quantity": {"__typename": "ItemDropQuantityRange", "min": 1000, "max": 2000}, "noted": false, "rarity": 0.047058823529411764}, {"id": 617, "members": true, "quantity": {"__typename": "ItemDropQuantityRange", "min": 5000, "max": 7000}, "noted": false, "rarity": 0.011764705882352941}, {"id": 1601, "members": true, "quantity": {"__typename": "ItemDropQuantityRange", "min": 3, "max": 6}, "noted": true, "rarity": 0.047058823529411764}, {"id": 373, "members": true, "quantity": {"__typename": "ItemDropQuantityRange", "min": 1, "max": 2}, "noted": false, "rarity": 0.047058823529411764}, {"id": 23083, "members": true, "quantity": {"__typename": "ItemDropQuantityScalar", "quantity": 1}, "noted": false, "rarity": 0.029205607476635514}, {"id": 2722, "members": true, "quantity": {"__typename": "ItemDropQuantityScalar", "quantity": 1}, "noted": false, "rarity": 0.0078125}, {"id": 199, "members": true, "quantity": {"__typename": "ItemDropQuantityRange", "min": 1, "max": 3}, "noted": false, "rarity": 0.014705882352941176}, {"id": 201, "members": true, "quantity": {"__typename": "ItemDropQuantityRange", "min": 1, "max": 3}, "noted": false, "rarity": 0.011030101146027508}, {"id": 203, "members": true, "quantity": {"__typename": "ItemDropQuantityRange", "min": 1, "max": 3}, "noted": false, "rarity": 0.008272188076468108}, {"id": 205, "members": true, "quantity": {"__typename": "ItemDropQuantityRange", "min": 1, "max": 3}, "noted": false, "rarity": 0.00643372300248985}, {"id": 207, "members": true, "quantity": {"__typename": "ItemDropQuantityRange", "min": 1, "max": 3}, "noted": false, "rarity": 0.00505356781888013}, {"id": 209, "members": true, "quantity": {"__typename": "ItemDropQuantityRange", "min": 1, "max": 3}, "noted": false, "rarity": 0.003676470588235294}, {"id": 211, "members": true, "quantity": {"__typename": "ItemDropQuantityRange", "min": 1, "max": 3}, "noted": false, "rarity": 0.0027577838449022365}, {"id": 213, "members": true, "quantity": {"__typename": "ItemDropQuantityRange", "min": 1, "max": 3}, "noted": false, "rarity": 0.002297794117647059}, {"id": 215, "members": true, "quantity": {"__typename": "ItemDropQuantityRange", "min": 1, "max": 3}, "noted": false, "rarity": 0.001838235294117647}, {"id": 2485, "members": true, "quantity": {"__typename": "ItemDropQuantityRange", "min": 1, "max": 3}, "noted": false, "rarity": 0.0013785687699030865}, {"id": 217, "members": true, "quantity": {"__typename": "ItemDropQuantityRange", "min": 1, "max": 3}, "noted": false, "rarity": 0.0013785687699030865}, {"id": 5296, "members": true, "quantity": {"__typename": "ItemDropQuantityScalar", "quantity": 1}, "noted": false, "rarity": 0.0023232041631818605}, {"id": 5297, "members": true, "quantity": {"__typename": "ItemDropQuantityScalar", "quantity": 1}, "noted": false, "rarity": 0.0015817028613004762}, {"id": 5281, "members": true, "quantity": {"__typename": "ItemDropQuantityScalar", "quantity": 1}, "noted": false, "rarity": 0.00153246136281789}, {"id": 5298, "members": true, "quantity": {"__typename": "ItemDropQuantityScalar", "quantity": 1}, "noted": false, "rarity": 0.0010873110796999022}, {"id": 5106, "members": true, "quantity": {"__typename": "ItemDropQuantityScalar", "quantity": 1}, "noted": false, "rarity": 0.0010873110796999022}, {"id": 5280, "members": true, "quantity": {"__typename": "ItemDropQuantityScalar", "quantity": 1}, "noted": false, "rarity": 0.001038367685997612}, {"id": 5299, "members": true, "quantity": {"__typename": "ItemDropQuantityScalar", "quantity": 1}, "noted": false, "rarity": 0.0007413173208792025}, {"id": 22873, "members": true, "quantity": {"__typename": "ItemDropQuantityScalar", "quantity": 1}, "noted": false, "rarity": 0.0007413173208792025}, {"id": 5300, "members": true, "quantity": {"__typename": "ItemDropQuantityScalar", "quantity": 1}, "noted": false, "rarity": 0.0004943153732081067}, {"id": 5301, "members": true, "quantity": {"__typename": "ItemDropQuantityScalar", "quantity": 1}, "noted": false, "rarity": 0.00034602076124567473}, {"id": 5302, "members": true, "quantity": {"__typename": "ItemDropQuantityScalar", "quantity": 1}, "noted": false, "rarity": 0.00024715768660405336}, {"id": 22879, "members": true, "quantity": {"__typename": "ItemDropQuantityScalar", "quantity": 3}, "noted": false, "rarity": 0.0001977261492832427}, {"id": 5303, "members": true, "quantity": {"__typename": "ItemDropQuantityScalar", "quantity": 1}, "noted": false, "rarity": 0.00014830084309029297}, {"id": 5304, "members": true, "quantity": {"__typename": "ItemDropQuantityScalar", "quantity": 1}, "noted": false, "rarity": 9.886307464162135e-05}, {"id": 20730, "members": true, "quantity": {"__typename": "ItemDropQuantityScalar", "quantity": 1}, "noted": false, "rarity": 0.0082540940306392}, {"id": 20736, "members": true, "quantity": {"__typename": "ItemDropQuantityScalar", "quantity": 1}, "noted": false, "rarity": 0.0082540940306392}, {"id": 21270, "members": true, "quantity": {"__typename": "ItemDropQuantityScalar", "quantity": 1}, "noted": false, "rarity": 0.002751364676879733}, {"id": 20724, "members": true, "quantity": {"__typename": "ItemDropQuantityScalar", "quantity": 1}, "noted": false, "rarity": 0.002751364676879733}]}