{"id": 11073, "name": "Sergeant", "qualified_name": "Sergeant (Shayzien)", "examine": "The other soldiers won't be messing around with him/her about.", "members": true, "release_date": "2021-06-16", "attributes": [], "size": 1, "aggressive": false, "poisonous": false, "venomous": false, "immune_poison": false, "immune_venom": false, "max_hit": 10, "attack_types": ["crush"], "attack_speed": 4, "wiki_url": "https://oldschool.runescape.wiki/w/Sergeant_(Shayzien)", "levels": {"combat": 84, "hitpoints": 86, "attack": 75, "strength": 73, "defence": 61, "magic": 1, "ranged": 1}, "bonuses": {"attack": {"melee": 17, "ranged": 0, "magic": 0}, "defence": {"stab": 16, "slash": 16, "crush": 18, "magic": -12, "ranged": 27}, "strength": {"melee": 15, "ranged": 0, "magic": 0}}, "drops": []}