{"id": 132, "name": "Hobgoblin", "qualified_name": "Hobgoblin guard", "examine": "He doesn't look very welcoming.", "members": true, "release_date": "2006-05-31", "attributes": [], "size": 1, "aggressive": true, "poisonous": false, "immune_poison": false, "immune_venom": false, "max_hit": 6, "attack_types": ["crush"], "attack_speed": 6, "wiki_url": "https://oldschool.runescape.wiki/w/Hobgoblin_guard", "levels": {"combat": 54, "hitpoints": 62, "attack": 45, "strength": 43, "defence": 43, "magic": 1, "ranged": 1}, "bonuses": {"attack": {"melee": 8, "ranged": 0, "magic": 0}, "defence": {"stab": 1, "slash": 1, "crush": 0, "magic": 0, "ranged": 0}, "strength": {"melee": 10, "ranged": 0, "magic": 0}}, "drops": []}