{"id": 1672, "name": "Ahrim the Blighted", "qualified_name": "Ahrim the Blighted", "examine": "A vengeful spirit corrupted by dark magic.", "members": true, "release_date": "2005-05-09", "attributes": [], "size": 1, "aggressive": true, "poisonous": false, "immune_poison": false, "immune_venom": false, "max_hit": 20, "attack_types": ["magic"], "attack_speed": 6, "wiki_url": "https://oldschool.runescape.wiki/w/Ahrim_the_Blighted", "slayer": {"masters": ["konar", "nieve", "duradel"], "level": 1, "xp": 102.5, "categories": ["boss"]}, "levels": {"combat": 98, "hitpoints": 100, "attack": 1, "strength": 1, "defence": 100, "magic": 100, "ranged": 1}, "bonuses": {"attack": {"melee": 0, "ranged": -19, "magic": 73}, "defence": {"stab": 103, "slash": 85, "crush": 117, "magic": 73, "ranged": 0}, "strength": {"melee": 68, "ranged": 0, "magic": 0}}, "drops": [{"id": 23083, "members": true, "quantity": {"__typename": "ItemDropQuantityScalar", "quantity": 1}, "noted": false, "rarity": 0.00992063492063492}]}