{"id": 2992, "name": "Undead cow", "qualified_name": "Undead cow", "examine": "It's an undead cow.", "members": true, "release_date": "2005-02-15", "attributes": ["undead"], "size": 2, "aggressive": false, "poisonous": false, "venomous": false, "immune_poison": false, "immune_venom": false, "max_hit": 1, "attack_types": ["crush"], "attack_speed": 4, "wiki_url": "https://oldschool.runescape.wiki/w/Undead_cow", "slayer": {"masters": ["turael", "spria", "mazchna"], "level": 1, "xp": 8.0, "categories": ["cows", "zombies"]}, "levels": {"combat": 2, "hitpoints": 8, "attack": 1, "strength": 1, "defence": 1, "magic": 1, "ranged": 1}, "bonuses": {"attack": {"melee": 0, "ranged": 0, "magic": 0}, "defence": {"stab": -21, "slash": -21, "crush": -21, "magic": -21, "ranged": -21}, "strength": {"melee": 0, "ranged": 0, "magic": 0}}, "drops": [{"id": 1739, "members": false, "quantity": {"__typename": "ItemDropQuantityScalar", "quantity": 1}, "noted": false, "rarity": 1.0, "rolls": 1}, {"id": 4287, "members": true, "quantity": {"__typename": "ItemDropQuantityScalar", "quantity": 1}, "noted": false, "rarity": 1.0, "rolls": 1}, {"id": 526, "members": false, "quantity": {"__typename": "ItemDropQuantityScalar", "quantity": 1}, "noted": false, "rarity": 1.0, "rolls": 1}, {"id": 7890, "members": true, "quantity": {"__typename": "ItemDropQuantityScalar", "quantity": 1}, "noted": false, "rarity": 0.25, "rolls": 1}]}