{"id": 428, "name": "Turoth", "qualified_name": "Turoth (Level 87)", "examine": "She's one leg short!", "members": true, "release_date": "2005-01-26", "attributes": ["leafy"], "size": 2, "aggressive": false, "poisonous": false, "immune_poison": false, "immune_venom": false, "max_hit": 10, "attack_types": ["melee"], "attack_speed": 4, "wiki_url": "https://oldschool.runescape.wiki/w/Turoth#Level_87", "slayer": {"masters": ["vannaka", "chaeldar", "konar", "nieve"], "level": 55, "xp": 79.0, "categories": ["turoth"]}, "levels": {"combat": 87, "hitpoints": 79, "attack": 56, "strength": 86, "defence": 86, "magic": 1, "ranged": 1}, "bonuses": {"attack": {"melee": 0, "ranged": 0, "magic": 0}, "defence": {"stab": 0, "slash": 20, "crush": 20, "magic": 0, "ranged": 0}, "strength": {"melee": 0, "ranged": 0, "magic": 0}}, "drops": [{"id": 526, "members": true, "quantity": {"__typename": "ItemDropQuantityScalar", "quantity": 1}, "noted": false, "rarity": 1.0}, {"id": 1069, "members": true, "quantity": {"__typename": "ItemDropQuantityScalar", "quantity": 1}, "noted": false, "rarity": 0.0546875}, {"id": 1355, "members": true, "quantity": {"__typename": "ItemDropQuantityScalar", "quantity": 1}, "noted": false, "rarity": 0.0234375}, {"id": 1197, "members": true, "quantity": {"__typename": "ItemDropQuantityScalar", "quantity": 1}, "noted": false, "rarity": 0.0078125}, {"id": 1161, "members": true, "quantity": {"__typename": "ItemDropQuantityScalar", "quantity": 1}, "noted": false, "rarity": 0.0078125}, {"id": 1213, "members": true, "quantity": {"__typename": "ItemDropQuantityScalar", "quantity": 1}, "noted": false, "rarity": 0.0078125}, {"id": 11902, "members": true, "quantity": {"__typename": "ItemDropQuantityScalar", "quantity": 1}, "noted": false, "rarity": 0.002}, {"id": 4113, "members": true, "quantity": {"__typename": "ItemDropQuantityScalar", "quantity": 1}, "noted": false, "rarity": 0.001953125}, {"id": 563, "members": true, "quantity": {"__typename": "ItemDropQuantityScalar", "quantity": 3}, "noted": false, "rarity": 0.046875}, {"id": 561, "members": true, "quantity": {"__typename": "ItemDropQuantityScalar", "quantity": 15}, "noted": false, "rarity": 0.0390625}, {"id": 561, "members": true, "quantity": {"__typename": "ItemDropQuantityScalar", "quantity": 37}, "noted": false, "rarity": 0.0078125}, {"id": 225, "members": true, "quantity": {"__typename": "ItemDropQuantityScalar", "quantity": 1}, "noted": false, "rarity": 0.0546875}, {"id": 617, "members": true, "quantity": {"__typename": "ItemDropQuantityScalar", "quantity": 44}, "noted": false, "rarity": 0.2265625}, {"id": 617, "members": true, "quantity": {"__typename": "ItemDropQuantityScalar", "quantity": 132}, "noted": false, "rarity": 0.09375}, {"id": 617, "members": true, "quantity": {"__typename": "ItemDropQuantityScalar", "quantity": 440}, "noted": false, "rarity": 0.0078125}, {"id": 2722, "members": true, "quantity": {"__typename": "ItemDropQuantityScalar", "quantity": 1}, "noted": false, "rarity": 0.0078125}, {"id": 23083, "members": true, "quantity": {"__typename": "ItemDropQuantityScalar", "quantity": 1}, "noted": false, "rarity": 0.007921419518377692}, {"id": 199, "members": true, "quantity": {"__typename": "ItemDropQuantityRange", "min": 1, "max": 3}, "noted": false, "rarity": 0.060546875}, {"id": 201, "members": true, "quantity": {"__typename": "ItemDropQuantityRange", "min": 1, "max": 3}, "noted": false, "rarity": 0.04541299456216013}, {"id": 203, "members": true, "quantity": {"__typename": "ItemDropQuantityRange", "min": 1, "max": 3}, "noted": false, "rarity": 0.03405814934608353}, {"id": 205, "members": true, "quantity": {"__typename": "ItemDropQuantityRange", "min": 1, "max": 3}, "noted": false, "rarity": 0.026488843924313683}, {"id": 207, "members": true, "quantity": {"__typename": "ItemDropQuantityRange", "min": 1, "max": 3}, "noted": false, "rarity": 0.02080648625429553}, {"id": 209, "members": true, "quantity": {"__typename": "ItemDropQuantityRange", "min": 1, "max": 3}, "noted": false, "rarity": 0.01513671875}, {"id": 211, "members": true, "quantity": {"__typename": "ItemDropQuantityRange", "min": 1, "max": 3}, "noted": false, "rarity": 0.011354313173933428}, {"id": 213, "members": true, "quantity": {"__typename": "ItemDropQuantityRange", "min": 1, "max": 3}, "noted": false, "rarity": 0.00946044921875}, {"id": 215, "members": true, "quantity": {"__typename": "ItemDropQuantityRange", "min": 1, "max": 3}, "noted": false, "rarity": 0.007568359375}, {"id": 2485, "members": true, "quantity": {"__typename": "ItemDropQuantityRange", "min": 1, "max": 3}, "noted": false, "rarity": 0.005675826107335364}, {"id": 217, "members": true, "quantity": {"__typename": "ItemDropQuantityRange", "min": 1, "max": 3}, "noted": false, "rarity": 0.005675826107335364}, {"id": 5296, "members": true, "quantity": {"__typename": "ItemDropQuantityScalar", "quantity": 1}, "noted": false, "rarity": 0.027769549763033176}, {"id": 5297, "members": true, "quantity": {"__typename": "ItemDropQuantityScalar", "quantity": 1}, "noted": false, "rarity": 0.018906292013982254}, {"id": 5281, "members": true, "quantity": {"__typename": "ItemDropQuantityScalar", "quantity": 1}, "noted": false, "rarity": 0.018317702227432592}, {"id": 5298, "members": true, "quantity": {"__typename": "ItemDropQuantityScalar", "quantity": 1}, "noted": false, "rarity": 0.012996765249537894}, {"id": 5106, "members": true, "quantity": {"__typename": "ItemDropQuantityScalar", "quantity": 1}, "noted": false, "rarity": 0.012996765249537894}, {"id": 5280, "members": true, "quantity": {"__typename": "ItemDropQuantityScalar", "quantity": 1}, "noted": false, "rarity": 0.012411738746690205}, {"id": 5299, "members": true, "quantity": {"__typename": "ItemDropQuantityScalar", "quantity": 1}, "noted": false, "rarity": 0.008861058601134217}, {"id": 22873, "members": true, "quantity": {"__typename": "ItemDropQuantityScalar", "quantity": 1}, "noted": false, "rarity": 0.008861058601134217}, {"id": 5300, "members": true, "quantity": {"__typename": "ItemDropQuantityScalar", "quantity": 1}, "noted": false, "rarity": 0.005908613445378151}, {"id": 5301, "members": true, "quantity": {"__typename": "ItemDropQuantityScalar", "quantity": 1}, "noted": false, "rarity": 0.004136029411764706}, {"id": 5302, "members": true, "quantity": {"__typename": "ItemDropQuantityScalar", "quantity": 1}, "noted": false, "rarity": 0.0029543067226890755}, {"id": 22879, "members": true, "quantity": {"__typename": "ItemDropQuantityScalar", "quantity": 3}, "noted": false, "rarity": 0.0023634453781512603}, {"id": 5303, "members": true, "quantity": {"__typename": "ItemDropQuantityScalar", "quantity": 1}, "noted": false, "rarity": 0.001772658515063658}, {"id": 5304, "members": true, "quantity": {"__typename": "ItemDropQuantityScalar", "quantity": 1}, "noted": false, "rarity": 0.0011817226890756302}]}