{"id": 872, "name": "Skogre", "qualified_name": "Skogre", "examine": "An undead skeletal ogre.", "members": true, "release_date": "2005-05-17", "attributes": ["undead"], "size": 2, "aggressive": true, "poisonous": false, "immune_poison": false, "immune_venom": false, "max_hit": 5, "attack_types": ["crush"], "attack_speed": 6, "wiki_url": "https://oldschool.runescape.wiki/w/Skogre", "slayer": {"masters": ["turael", "spria", "vannaka"], "level": 1, "xp": 71.0, "categories": ["ogre", "skeleton"]}, "levels": {"combat": 44, "hitpoints": 71, "attack": 20, "strength": 36, "defence": 35, "magic": 1, "ranged": 1}, "bonuses": {"attack": {"melee": 0, "ranged": 0, "magic": 0}, "defence": {"stab": 0, "slash": 0, "crush": 0, "magic": 0, "ranged": 0}, "strength": {"melee": 0, "ranged": 0, "magic": 0}}, "drops": [{"id": 4812, "members": true, "quantity": {"__typename": "ItemDropQuantityScalar", "quantity": 1}, "noted": false, "rarity": 1.0}, {"id": 4850, "members": true, "quantity": {"__typename": "ItemDropQuantityScalar", "quantity": 1}, "noted": false, "rarity": 1.0}]}