{"id": 22628, "name": "Statius's platebody", "qualified_name": "Statius's platebody", "examine": "A powerful platebody.", "members": true, "release_date": "2018-09-06", "quest": false, "weight": 9.979, "value": 500000, "alchemy": {"high": 300000, "low": 200000}, "tradeable": true, "stackable": false, "noteable": true, "equipable": true, "tradeable_ge": false, "icon": "iVBORw0KGgoAAAANSUhEUgAAACQAAAAgCAYAAAB6kdqOAAAAGklEQVR4Xu3BAQEAAACCIP+vbkhAAQAAAPBsEiAAARQpr9AAAAAASUVORK5CYII=", "wiki_url": "https://oldschool.runescape.wiki/w/Statius's_platebody", "equipment": {"slot": "body", "requirements": [{"skill": "defence", "level": 78}], "bonuses": {"attack": {"stab": 5, "slash": 5, "crush": 7, "magic": -30, "ranged": -10}, "defence": {"stab": 154, "slash": 145, "crush": 121, "magic": -6, "ranged": 157}, "strength": {"melee": 5, "ranged": 0, "magic": 0}, "prayer": 0}}}