{"id": 22792, "name": "Half a dragonfruit pie", "qualified_name": "Dragonfruit pie (Half)", "examine": "Mmm half a dragonfruit pie.", "members": true, "release_date": "2019-01-10", "quest": false, "weight": 0.225, "value": 35, "alchemy": {"high": 21, "low": 14}, "tradeable": true, "stackable": false, "noteable": true, "equipable": false, "tradeable_ge": false, "icon": "iVBORw0KGgoAAAANSUhEUgAAACQAAAAgCAYAAAB6kdqOAAAAGklEQVR4Xu3BAQEAAACCIP+vbkhAAQAAAPBsEiAAARQpr9AAAAAASUVORK5CYII=", "wiki_url": "https://oldschool.runescape.wiki/w/Dragonfruit_pie#Half"}