{"id": 23849, "name": "Corrupted halberd (basic)", "qualified_name": "Corrupted halberd (basic)", "examine": "A wooden stick with some corrupted on the end.", "members": true, "release_date": "2019-07-25", "quest": false, "weight": 1.814, "value": 1, "tradeable": false, "stackable": false, "noteable": false, "equipable": true, "tradeable_ge": false, "icon": "iVBORw0KGgoAAAANSUhEUgAAACQAAAAgCAYAAAB6kdqOAAAAGklEQVR4Xu3BAQEAAACCIP+vbkhAAQAAAPBsEiAAARQpr9AAAAAASUVORK5CYII=", "wiki_url": "https://oldschool.runescape.wiki/w/Corrupted_halberd_(basic)", "equipment": {"slot": "twohanded", "requirements": [], "bonuses": {"attack": {"stab": 68, "slash": 68, "crush": 4, "magic": 0, "ranged": 0}, "defence": {"stab": 0, "slash": 0, "crush": 0, "magic": 0, "ranged": 0}, "strength": {"melee": 42, "ranged": 0, "magic": 0}, "prayer": 1}, "weapon": {"speed": 4, "category": {"name": "polearm"}}}}