{"id": 25934, "name": "Ghommal's hilt 5", "qualified_name": "Ghommal's hilt 5", "examine": "A sublime artifact.", "members": true, "release_date": "2021-07-21", "quest": false, "weight": 0.001, "value": 0, "tradeable": false, "stackable": false, "noteable": false, "equipable": true, "tradeable_ge": false, "icon": "iVBORw0KGgoAAAANSUhEUgAAACQAAAAgCAYAAAB6kdqOAAAAGklEQVR4Xu3BAQEAAACCIP+vbkhAAQAAAPBsEiAAARQpr9AAAAAASUVORK5CYII=", "wiki_url": "https://oldschool.runescape.wiki/w/Ghommal's_hilt_5", "equipment": {"slot": "offhand", "requirements": [], "bonuses": {"attack": {"stab": 0, "slash": 0, "crush": 0, "magic": 0, "ranged": 0}, "defence": {"stab": 0, "slash": 0, "crush": 0, "magic": 0, "ranged": 0}, "strength": {"melee": 0, "ranged": 0, "magic": 0}, "prayer": 0}}}